{
    "id": 17968,
    "condition": "[GT](<*VALUE(PCD_Total_Qty_of_Modules)*>,8)",
    "name": "Add_HPCD3.C100",
    "action": "<* DoNotResetAtt *><*SELECTVALUE(PCD_Part_Summary:HPCD3.C100)*>[IF]([GT](<* Eval((<*VALUE(PCD_Total_Qty_of_Modules)*>-((<*GETATVQTY(PCD_Part_Summary:HPCD3.M6893)*>*4)+(<*GETATVQTY(PCD_Part_Summary:HPCD3.C200)*>*4)))/4) *>,<* Eval(INT((<*VALUE(PCD_Total_Qty_of_Modules)*>-((<*GETATVQTY(PCD_Part_Summary:HPCD3.M6893)*>*4)+(<*GETATVQTY(PCD_Part_Summary:HPCD3.C200)*>*4)))/4)) *>)){<*SETATVQTY(PCD_Part_Summary:HPCD3.C100,<* Eval(INT((<*VALUE(PCD_Total_Qty_of_Modules)*>-((<*GETATVQTY(PCD_Part_Summary:HPCD3.M6893)*>*4)+(<*GETATVQTY(PCD_Part_Summary:HPCD3.C200)*>*4)))/4)+1) *>)*>}{<*SETATVQTY(PCD_Part_Summary:HPCD3.C100,<* Eval(INT((<*VALUE(PCD_Total_Qty_of_Modules)*>-((<*GETATVQTY(PCD_Part_Summary:HPCD3.M6893)*>*4)+(<*GETATVQTY(PCD_Part_Summary:HPCD3.C200)*>*4)))/4)) *>)*>}[ENDIF]<* DoResetAtt *>",
    "description": "",
    "rank": "6",
    "active": true,
    "modifiedDate": "-",
    "modifiedBy": ""
}