{
    "id": 26088,
    "condition": "[AND](<*ISSELECTED(Interface with TPS Required?.Yes)*>,[AND]([LT](<*VALUE(ACE Node Tower Mount Desk)*>,1),[LT](<*VALUE(ACE Node Rack Mount Cabinet)*>,1),[LT](<*VALUE(ACE_T_Node _Tower_Mount_Desk)*>,1),[LT](<*VALUE(ACE_T_Node _Rack_Mount_Cabinet)*>,1)))",
    "name": "TC-SWSC01_Remove",
    "action": "<* DoNotResetAtt *><*RESETVALUE(Exp_Ent_Grp_Part_Summary:TC-SWSC01)*><* DoResetAtt *>",
    "description": "",
    "rank": "0",
    "active": true,
    "modifiedDate": "-",
    "modifiedBy": ""
}