{
    "id": 26436,
    "condition": "[AND]([EQ](<*VALUE(Rack_Mounting_Type)*>,Slide Mount),[OR](<*ISSELECTED(Exp_Ent_Grp_Part_Summary.MP-C1MCB1-100)*>,<*ISSELECTED(Exp_Ent_Grp_Part_Summary.MP-C1MCB1-200)*>,<*ISSELECTED(Exp_Ent_Grp_Part_Summary.MP-C8LCB1-100)*>,<*ISSELECTED(Exp_Ent_Grp_Part_Summary.MP-C8LCB1-200)*>,<*ISSELECTED(Exp_Ent_Grp_Part_Summary.MP-C1MCB1-103)*>,<*ISSELECTED(Exp_Ent_Grp_Part_Summary.MP-C1MCB1-203)*>,<*ISSELECTED(Exp_Ent_Grp_Part_Summary.MP-C8LCB1-103)*>,<*ISSELECTED(Exp_Ent_Grp_Part_Summary.MP-C8LCB1-203)*>,<*ISSELECTED(Exp_Ent_Grp_Part_Summary.MP-C1MCB1-102)*>,<*ISSELECTED(Exp_Ent_Grp_Part_Summary.MP-C1MCB1-202)*>,<*ISSELECTED(Exp_Ent_Grp_Part_Summary.MP-C8LCB1-102)*>,<*ISSELECTED(Exp_Ent_Grp_Part_Summary.MP-C8LCB1-202)*>,<*ISSELECTED(Exp_Ent_Grp_Part_Summary.MP-C1MCB1-101)*>,<*ISSELECTED(Exp_Ent_Grp_Part_Summary.MP-C1MCB1-201)*>,<*ISSELECTED(Exp_Ent_Grp_Part_Summary.MP-C8LCB1-101)*>,<*ISSELECTED(Exp_Ent_Grp_Part_Summary.MP-C8LCB1-201)*>))",
    "name": "TP-SPCMS1-101 rack part add",
    "action": "<* DoNotResetAtt *><*SELECTVALUES(Exp_Ent_Grp_Part_Summary:TP-SPCMS1-101)*><*SETATVQTY(Exp_Ent_Grp_Part_Summary:TP-SPCMS1-101,<* Eval(<*VALUE(exp_ent_cab_qnt)*>+<*VALUE(Network_Cabinet_Qty)*>) *>)*><* DoResetAtt *>",
    "description": "CXCPQ-38428",
    "rank": "1000",
    "active": false,
    "modifiedDate": "-",
    "modifiedBy": ""
}